{
  "fall_9.000": "Em... Doktorze Harvey? To jest całkowicie prywatne, prawda?",
  "15.000": "Lubię sprawdzać jak się mają lokalne biznesy w naszym miasteczku.",
  "6.000": "Jestem tu, by odebrać podatek Clint'a.",
  "1.000": "Cóż, o tej porze roku najbardziej czuć ryby.",
  "Tue.000": "Robię tu wszystkie moje zakupy.$h",
  "3.000": "Jestem tu by upewnić się, czy potrzeby biznesu Marnie są spełnione.",
  "6.001": "Biblioteka to jedna z najlepszych atrakcji Miasta Pelikan. Jest ufundowana z podatków, które zbieramy z lokalnych biznesów.",
  "winter_16.000": "Wiesz, kupiłem wszystkie moje ulubione rzeczy z targu..."
}